ferreus_bbfmm-0.1.1.dist-info/METADATA
ferreus_bbfmm-0.1.1.dist-info/WHEEL
ferreus_bbfmm/__init__.py
ferreus_bbfmm/ferreus_bbfmm.abi3.so
ferreus_bbfmm/ferreus_bbfmm.pyi
ferreus_bbfmm-0.1.1.dist-info/RECORD
