Metadata-Version: 2.4
Name: ferreus_bbfmm
Version: 0.1.1
Classifier: Programming Language :: Rust
Classifier: Programming Language :: Python :: Implementation :: CPython
Classifier: Programming Language :: Python :: Implementation :: PyPy
Summary: Parallel black box fast multipole method (BBFMM) library
Keywords: fmm,bbfmm,fast-multipole-method,matrix-vector-product
Author-email: Daniel Owen <daniel.owen@live.com.au>
License-Expression: MIT
Requires-Python: >=3.8
Project-URL: Homepage, https://github.com/graphic-goose/ferreus_rbf_rs
Project-URL: Documentation, https://graphic-goose.github.io/ferreus_rbf_rs/ferreus_bbfmm/
